{
    "pipes": [],
    "interfaces": [],
    "injectables": [],
    "guards": [],
    "interceptors": [],
    "classes": [],
    "directives": [],
    "components": [
        {
            "name": "AppComponent",
            "id": "component-AppComponent-f6c9c072827b299c5d5faf103e7bfc028daf0d8922fbe2431a3b3500b0903953f4dc844c9945e4b24e53a8b96635253bdd7c694a4411b2e36fb5157dd2746de4",
            "file": "src/app/app.component.ts",
            "encapsulation": [],
            "entryComponents": [],
            "inputs": [],
            "outputs": [],
            "providers": [],
            "selector": "app-root",
            "styleUrls": [
                "./app.component.scss"
            ],
            "styles": [],
            "templateUrl": [
                "./app.component.html"
            ],
            "viewProviders": [],
            "inputsClass": [],
            "outputsClass": [],
            "propertiesClass": [
                {
                    "name": "title",
                    "defaultValue": "'daniel-storybook'",
                    "deprecated": false,
                    "deprecationMessage": "",
                    "type": "string",
                    "optional": false,
                    "description": "",
                    "line": 9
                }
            ],
            "methodsClass": [],
            "deprecated": false,
            "deprecationMessage": "",
            "hostBindings": [],
            "hostListeners": [],
            "description": "",
            "rawdescription": "\n",
            "type": "component",
            "sourceCode": "import { Component } from '@angular/core';\n\n@Component({\n  selector: 'app-root',\n  templateUrl: './app.component.html',\n  styleUrls: ['./app.component.scss']\n})\nexport class AppComponent {\n  title = 'daniel-storybook';\n}\n",
            "assetsDirs": [],
            "styleUrlsData": [
                {
                    "data": "",
                    "styleUrl": "./app.component.scss"
                }
            ],
            "stylesData": "",
            "templateData": "<ui-sidenav></ui-sidenav>"
        },
        {
            "name": "SidenavComponent",
            "id": "component-SidenavComponent-6faa6c8ebd4d61227e487066801e8809adc61006ab4e2e2290a78cc907299260bfb3980f4173df4a1c62b3bf96b44143460c4ca01ab35ad6c4b07f4d6af44f84",
            "file": "projects/ui-components/src/lib/components/sidenav/sidenav.component.ts",
            "encapsulation": [],
            "entryComponents": [],
            "inputs": [],
            "outputs": [],
            "providers": [],
            "selector": "ui-sidenav",
            "styleUrls": [
                "./sidenav.component.scss"
            ],
            "styles": [],
            "templateUrl": [
                "./sidenav.component.html"
            ],
            "viewProviders": [],
            "inputsClass": [],
            "outputsClass": [],
            "propertiesClass": [],
            "methodsClass": [],
            "deprecated": false,
            "deprecationMessage": "",
            "hostBindings": [],
            "hostListeners": [],
            "description": "",
            "rawdescription": "\n",
            "type": "component",
            "sourceCode": "import { Component } from '@angular/core';\n\n@Component({\n  selector: 'ui-sidenav',\n  templateUrl: './sidenav.component.html',\n  styleUrls: ['./sidenav.component.scss'],\n})\nexport class SidenavComponent {}\n",
            "assetsDirs": [],
            "styleUrlsData": [
                {
                    "data": "@import url(\"https://fonts.googleapis.com/css2?family=Open+Sans:ital,wght@0,300;0,400;0,500;0,600;0,700;0,800;1,300;1,400;1,500;1,600;1,700;1,800&display=swap\");\n\n.sidenav {\n  font-family: \"Open Sans\", sans-serif;\n  position: fixed;\n  top: 0;\n  left: 0;\n  width: 260px;\n  height: 100%;\n  background: #211f25;\n  color: #ffffff;\n  transition: width 0.4s;\n}\n\n.sidenav header {\n  display: flex;\n  align-items: center;\n  height: 72px;\n  padding: 0 1.25rem 0 0;\n  border-bottom: 1px solid rgb(255 255 255 / 12%);\n}\n",
                    "styleUrl": "./sidenav.component.scss"
                }
            ],
            "stylesData": "",
            "templateData": "<aside class=\"sidenav\">\n  <header class=\"header\">Header</header>\n  <ui-sidenav-item title=\"Home\">\n    <ui-sidenav-subitem title=\"Teste1\"></ui-sidenav-subitem>\n  </ui-sidenav-item>\n  <ui-sidenav-item title=\"Settings\">\n    <ui-sidenav-subitem title=\"Teste1\"></ui-sidenav-subitem>\n    <ui-sidenav-subitem title=\"Teste2\"></ui-sidenav-subitem>\n  </ui-sidenav-item>\n  <ui-sidenav-item title=\"Exit\"> </ui-sidenav-item>\n</aside>\n"
        },
        {
            "name": "SidenavItemComponent",
            "id": "component-SidenavItemComponent-7907c4f34911838154fbcbaa992b3d331ab8fc8798dbbbe6b77ead8520de1903dc2343718074d2ffcb99c0e08115badb894050ea6b776cca83b8203c08a1ae3a",
            "file": "projects/ui-components/src/lib/components/sidenav/sidenav-item/sidenav-item.component.ts",
            "encapsulation": [],
            "entryComponents": [],
            "inputs": [],
            "outputs": [],
            "providers": [],
            "selector": "ui-sidenav-item",
            "styleUrls": [
                "./sidenav-item.component.scss"
            ],
            "styles": [],
            "templateUrl": [
                "./sidenav-item.component.html"
            ],
            "viewProviders": [],
            "inputsClass": [
                {
                    "name": "collapsed",
                    "defaultValue": "true",
                    "deprecated": false,
                    "deprecationMessage": "",
                    "line": 24,
                    "type": "boolean",
                    "decorators": []
                },
                {
                    "name": "icon",
                    "defaultValue": "''",
                    "deprecated": false,
                    "deprecationMessage": "",
                    "line": 22,
                    "type": "string",
                    "decorators": []
                },
                {
                    "name": "navigation",
                    "defaultValue": "'/'",
                    "deprecated": false,
                    "deprecationMessage": "",
                    "line": 23,
                    "type": "string",
                    "decorators": []
                },
                {
                    "name": "title",
                    "defaultValue": "''",
                    "deprecated": false,
                    "deprecationMessage": "",
                    "line": 21,
                    "type": "string",
                    "decorators": []
                }
            ],
            "outputsClass": [
                {
                    "name": "openSubItem",
                    "defaultValue": "new EventEmitter<string>()",
                    "deprecated": false,
                    "deprecationMessage": "",
                    "line": 25,
                    "type": "EventEmitter<string>"
                }
            ],
            "propertiesClass": [
                {
                    "name": "idComponent",
                    "defaultValue": "uuidv4()",
                    "deprecated": false,
                    "deprecationMessage": "",
                    "type": "string",
                    "optional": false,
                    "description": "",
                    "line": 27
                },
                {
                    "name": "subitemsElementRef",
                    "deprecated": false,
                    "deprecationMessage": "",
                    "type": "ElementRef",
                    "optional": false,
                    "description": "",
                    "line": 20,
                    "decorators": [
                        {
                            "name": "ViewChild",
                            "stringifiedArguments": "'subitems', {static: false}"
                        }
                    ]
                }
            ],
            "methodsClass": [
                {
                    "name": "closeSubItems",
                    "args": [],
                    "optional": false,
                    "returnType": "void",
                    "typeParameters": [],
                    "line": 60,
                    "deprecated": false,
                    "deprecationMessage": ""
                },
                {
                    "name": "ngOnChanges",
                    "args": [
                        {
                            "name": "changes",
                            "type": "SimpleChanges",
                            "deprecated": false,
                            "deprecationMessage": ""
                        }
                    ],
                    "optional": false,
                    "returnType": "void",
                    "typeParameters": [],
                    "line": 31,
                    "deprecated": false,
                    "deprecationMessage": "",
                    "jsdoctags": [
                        {
                            "name": "changes",
                            "type": "SimpleChanges",
                            "deprecated": false,
                            "deprecationMessage": "",
                            "tagName": {
                                "text": "param"
                            }
                        }
                    ]
                },
                {
                    "name": "ngOnInit",
                    "args": [],
                    "optional": false,
                    "returnType": "void",
                    "typeParameters": [],
                    "line": 29,
                    "deprecated": false,
                    "deprecationMessage": ""
                },
                {
                    "name": "openSubItems",
                    "args": [],
                    "optional": false,
                    "returnType": "void",
                    "typeParameters": [],
                    "line": 51,
                    "deprecated": false,
                    "deprecationMessage": ""
                },
                {
                    "name": "setHeightToSubitems",
                    "args": [
                        {
                            "name": "height",
                            "type": "number",
                            "deprecated": false,
                            "deprecationMessage": ""
                        }
                    ],
                    "optional": false,
                    "returnType": "void",
                    "typeParameters": [],
                    "line": 64,
                    "deprecated": false,
                    "deprecationMessage": "",
                    "jsdoctags": [
                        {
                            "name": "height",
                            "type": "number",
                            "deprecated": false,
                            "deprecationMessage": "",
                            "tagName": {
                                "text": "param"
                            }
                        }
                    ]
                },
                {
                    "name": "toggleSubitems",
                    "args": [
                        {
                            "name": "collapsed",
                            "type": "boolean",
                            "deprecated": false,
                            "deprecationMessage": ""
                        }
                    ],
                    "optional": false,
                    "returnType": "void",
                    "typeParameters": [],
                    "line": 42,
                    "deprecated": false,
                    "deprecationMessage": "",
                    "jsdoctags": [
                        {
                            "name": "collapsed",
                            "type": "boolean",
                            "deprecated": false,
                            "deprecationMessage": "",
                            "tagName": {
                                "text": "param"
                            }
                        }
                    ]
                }
            ],
            "deprecated": false,
            "deprecationMessage": "",
            "hostBindings": [],
            "hostListeners": [],
            "description": "",
            "rawdescription": "\n",
            "type": "component",
            "sourceCode": "import {\n  Component,\n  ElementRef,\n  EventEmitter,\n  Input,\n  OnChanges,\n  OnInit,\n  Output,\n  SimpleChanges,\n  ViewChild,\n} from '@angular/core';\nimport { v4 as uuidv4 } from 'uuid';\n\n@Component({\n  selector: 'ui-sidenav-item',\n  templateUrl: './sidenav-item.component.html',\n  styleUrls: ['./sidenav-item.component.scss'],\n})\nexport class SidenavItemComponent implements OnInit {\n  @ViewChild('subitems', { static: false }) subitemsElementRef!: ElementRef;\n  @Input() title: string = '';\n  @Input() icon: string = '';\n  @Input() navigation: string = '/';\n  @Input() collapsed: boolean = true;\n  @Output() openSubItem: EventEmitter<string> = new EventEmitter<string>();\n\n  idComponent: string = uuidv4();\n\n  ngOnInit() {}\n\n  ngOnChanges(changes: SimpleChanges) {\n    //detectar mudanca para aberto e realizar os ajustes\n    if (changes['collapsed']?.currentValue === true) {\n      if (\n        changes['collapsed'].currentValue !== changes['collapsed'].previousValue\n      ) {\n        this.closeSubItems();\n      }\n    }\n  }\n\n  toggleSubitems(collapsed: boolean) {\n    this.collapsed = collapsed;\n    if (collapsed === false) {\n      this.openSubItems();\n    } else {\n      this.closeSubItems();\n    }\n  }\n\n  openSubItems() {\n    this.openSubItem.emit(this.idComponent);\n\n    const innerDivSubitems: HTMLElement =\n      this.subitemsElementRef.nativeElement.querySelector('#subitems-inner');\n    const innerHeight = innerDivSubitems.clientHeight;\n    this.setHeightToSubitems(innerHeight);\n  }\n\n  closeSubItems() {\n    this.setHeightToSubitems(0);\n  }\n\n  setHeightToSubitems(height: number) {\n    this.subitemsElementRef.nativeElement.style.height = `${height}px`;\n  }\n}\n",
            "assetsDirs": [],
            "styleUrlsData": [
                {
                    "data": "button {\n  background: transparent;\n  border: 0;\n  cursor: pointer;\n  text-align: left;\n  position: relative;\n  display: flex;\n  gap: 16px;\n  align-items: center;\n  height: 50px;\n  width: 100%;\n  font-family: inherit;\n  font-size: 16px;\n  font-weight: 400;\n  line-height: 1;\n  padding: 0 16px 0 25px;\n  color: inherit;\n  background-color: inherit;\n  transition: 0.25s;\n}\n\nbutton.active,\n.subnav {\n  background: #32303c;\n}\n\nbutton:hover {\n  background: #3c3a48;\n}\n\n.subitems {\n  position: relative;\n  overflow: hidden;\n  height: 0;\n  transition: 0.4s;\n}\n",
                    "styleUrl": "./sidenav-item.component.scss"
                }
            ],
            "stylesData": "",
            "implements": [
                "OnInit"
            ],
            "templateData": "<button class=\"sidenav-item\" (click)=\"toggleSubitems(!collapsed)\">\n  {{ title }}\n</button>\n<div\n  [id]=\"idComponent\"\n  #subitems\n  class=\"subitems\"\n  [ngClass]=\"{ open: !collapsed }\"\n>\n  <div id=\"subitems-inner\" class=\"subitems-inner\">\n    <ng-content></ng-content>\n  </div>\n</div>\n"
        },
        {
            "name": "SidenavSubitemComponent",
            "id": "component-SidenavSubitemComponent-ac62e491f71aecf4710713c16bfb222d9f1eb465fc108e251d7f617792ea51ac27fc582e01a79a9ad05ca31128817fe25430d1dd3f55b132e4ee5268029cb9df",
            "file": "projects/ui-components/src/lib/components/sidenav/sidenav-subitem/sidenav-subitem.component.ts",
            "encapsulation": [],
            "entryComponents": [],
            "inputs": [],
            "outputs": [],
            "providers": [],
            "selector": "ui-sidenav-subitem",
            "styleUrls": [
                "./sidenav-subitem.component.scss"
            ],
            "styles": [],
            "templateUrl": [
                "./sidenav-subitem.component.html"
            ],
            "viewProviders": [],
            "inputsClass": [
                {
                    "name": "navigation",
                    "defaultValue": "'/'",
                    "deprecated": false,
                    "deprecationMessage": "",
                    "line": 10,
                    "type": "string",
                    "decorators": []
                },
                {
                    "name": "title",
                    "defaultValue": "''",
                    "deprecated": false,
                    "deprecationMessage": "",
                    "line": 9,
                    "type": "string",
                    "decorators": []
                }
            ],
            "outputsClass": [],
            "propertiesClass": [],
            "methodsClass": [],
            "deprecated": false,
            "deprecationMessage": "",
            "hostBindings": [],
            "hostListeners": [],
            "description": "",
            "rawdescription": "\n",
            "type": "component",
            "sourceCode": "import { Component, Input } from '@angular/core';\n\n@Component({\n  selector: 'ui-sidenav-subitem',\n  templateUrl: './sidenav-subitem.component.html',\n  styleUrls: ['./sidenav-subitem.component.scss'],\n})\nexport class SidenavSubitemComponent {\n  @Input() title: string = '';\n  @Input() navigation: string = '/';\n}\n",
            "assetsDirs": [],
            "styleUrlsData": [
                {
                    "data": ":host {\n  width: 100%;\n}\n\n.sidenav-subitem {\n  border: 0;\n  cursor: pointer;\n  text-align: left;\n  position: relative;\n  display: flex;\n  gap: 16px;\n  align-items: center;\n  height: 50px;\n  width: 100%;\n  font-family: inherit;\n  font-size: 16px;\n  font-weight: 400;\n  line-height: 1;\n  padding: 0 16px 0 64px;\n  color: inherit;\n  background-color: #2d2d2d74;\n}\n\n.sidenav-subitem.active,\n.subnav {\n  background: #32303c;\n}\n\n.sidenav-subitem:hover {\n  background: #3c3a48;\n}\n\n.sidenav-subitem::before {\n  content: \"\";\n  position: absolute;\n  top: 50%;\n  left: 36px;\n  translate: 0 -50%;\n  width: 5px;\n  height: 5px;\n  border-radius: 50%;\n  background-color: rgb(255 255 255 / 40%);\n}\n",
                    "styleUrl": "./sidenav-subitem.component.scss"
                }
            ],
            "stylesData": "",
            "templateData": "<button class=\"sidenav-subitem\">\n  {{ title }}\n</button>\n"
        },
        {
            "name": "TypographyComponent",
            "id": "component-TypographyComponent-bc2f41a9410e0bdc31b26ecd324d90ee35c10110b345350f0b25d0eb349b9d93547048cd8173f0fc17eb722a6492db906bc53ed4c7fc15e5a4af8846fb957a51",
            "file": "projects/ui-components/src/lib/components/typography/typography.component.ts",
            "encapsulation": [],
            "entryComponents": [],
            "inputs": [],
            "outputs": [],
            "providers": [],
            "selector": "ui-typography",
            "styleUrls": [
                "./typography.component.scss"
            ],
            "styles": [],
            "templateUrl": [
                "./typography.component.html"
            ],
            "viewProviders": [],
            "inputsClass": [],
            "outputsClass": [],
            "propertiesClass": [],
            "methodsClass": [],
            "deprecated": false,
            "deprecationMessage": "",
            "hostBindings": [],
            "hostListeners": [],
            "description": "",
            "rawdescription": "\n",
            "type": "component",
            "sourceCode": "import { Component } from '@angular/core';\n\n@Component({\n  selector: 'ui-typography',\n  templateUrl: './typography.component.html',\n  styleUrls: ['./typography.component.scss']\n})\nexport class TypographyComponent {\n\n}\n",
            "assetsDirs": [],
            "styleUrlsData": [
                {
                    "data": "",
                    "styleUrl": "./typography.component.scss"
                }
            ],
            "stylesData": "",
            "templateData": "<p>typography works!</p>\n"
        }
    ],
    "modules": [
        {
            "name": "AppModule",
            "id": "module-AppModule-9f1ee8ee316d202d1a3f865e65607d60798813ab1152669f4ce78ed41909b9db34bd1b19a3f80b679f665af4cc2614366c40e09fa51fe028e4541bf0a9c3d13a",
            "description": "",
            "deprecationMessage": "",
            "deprecated": false,
            "file": "src/app/app.module.ts",
            "methods": [],
            "sourceCode": "import { NgModule } from '@angular/core';\nimport { BrowserModule } from '@angular/platform-browser';\nimport { UiComponentsModule } from 'ui-components/ui-components.module';\n\nimport { AppComponent } from './app.component';\n\n@NgModule({\n  declarations: [\n    AppComponent\n  ],\n  imports: [\n    BrowserModule,\n    UiComponentsModule\n  ],\n  providers: [],\n  bootstrap: [AppComponent]\n})\nexport class AppModule { }\n",
            "children": [
                {
                    "type": "providers",
                    "elements": []
                },
                {
                    "type": "declarations",
                    "elements": [
                        {
                            "name": "AppComponent"
                        }
                    ]
                },
                {
                    "type": "imports",
                    "elements": []
                },
                {
                    "type": "exports",
                    "elements": []
                },
                {
                    "type": "bootstrap",
                    "elements": [
                        {
                            "name": "AppComponent"
                        }
                    ]
                },
                {
                    "type": "classes",
                    "elements": []
                }
            ]
        },
        {
            "name": "SidenavModule",
            "id": "module-SidenavModule-d52ac7055553102a5e9672e836a8c1cdaf09e54af6553813fc620293504b83b353dd2f516202b2295625ecab5c47aaab4faf837a233bea5592bd382b1314c034",
            "description": "",
            "deprecationMessage": "",
            "deprecated": false,
            "file": "projects/ui-components/src/lib/components/sidenav/sidenav.module.ts",
            "methods": [],
            "sourceCode": "import { NgModule } from '@angular/core';\nimport { CommonModule } from '@angular/common';\nimport { SidenavComponent } from './sidenav.component';\nimport { SidenavItemComponent } from './sidenav-item/sidenav-item.component';\nimport { SidenavSubitemComponent } from './sidenav-subitem/sidenav-subitem.component';\n\n@NgModule({\n  declarations: [\n    SidenavComponent,\n    SidenavItemComponent,\n    SidenavSubitemComponent,\n  ],\n  imports: [CommonModule],\n  exports: [SidenavComponent, SidenavItemComponent, SidenavSubitemComponent],\n})\nexport class SidenavModule {}\n",
            "children": [
                {
                    "type": "providers",
                    "elements": []
                },
                {
                    "type": "declarations",
                    "elements": [
                        {
                            "name": "SidenavComponent"
                        },
                        {
                            "name": "SidenavItemComponent"
                        },
                        {
                            "name": "SidenavSubitemComponent"
                        }
                    ]
                },
                {
                    "type": "imports",
                    "elements": []
                },
                {
                    "type": "exports",
                    "elements": [
                        {
                            "name": "SidenavComponent"
                        },
                        {
                            "name": "SidenavItemComponent"
                        },
                        {
                            "name": "SidenavSubitemComponent"
                        }
                    ]
                },
                {
                    "type": "bootstrap",
                    "elements": []
                },
                {
                    "type": "classes",
                    "elements": []
                }
            ]
        },
        {
            "name": "UiComponentsModule",
            "id": "module-UiComponentsModule-ae1b1ac2fbaa60960060fc10841ff2a7aac54e7e09214591a6a94789eb458db77845376023f61ed79eb97d024817c886ddeec3f028696e776090a629b4c6bce8",
            "description": "",
            "deprecationMessage": "",
            "deprecated": false,
            "file": "projects/ui-components/src/lib/ui-components.module.ts",
            "methods": [],
            "sourceCode": "import { NgModule } from '@angular/core';\nimport { SidenavModule } from './components/sidenav/sidenav.module';\nimport { TypographyComponent } from './components/typography/typography.component';\n\n@NgModule({\n  declarations: [\n    \n  \n    TypographyComponent\n  ],\n  imports: [\n    SidenavModule\n  ],\n  exports: [\n    SidenavModule\n  ]\n})\nexport class UiComponentsModule { }\n",
            "children": [
                {
                    "type": "providers",
                    "elements": []
                },
                {
                    "type": "declarations",
                    "elements": [
                        {
                            "name": "TypographyComponent"
                        }
                    ]
                },
                {
                    "type": "imports",
                    "elements": [
                        {
                            "name": "SidenavModule"
                        }
                    ]
                },
                {
                    "type": "exports",
                    "elements": [
                        {
                            "name": "SidenavModule"
                        }
                    ]
                },
                {
                    "type": "bootstrap",
                    "elements": []
                },
                {
                    "type": "classes",
                    "elements": []
                }
            ]
        }
    ],
    "miscellaneous": {
        "variables": [
            {
                "name": "Default",
                "ctype": "miscellaneous",
                "subtype": "variable",
                "file": "projects/ui-components/src/lib/components/sidenav/sidenav.stories.ts",
                "deprecated": false,
                "deprecationMessage": "",
                "type": "",
                "defaultValue": "Template.bind({})"
            },
            {
                "name": "Template",
                "ctype": "miscellaneous",
                "subtype": "variable",
                "file": "projects/ui-components/src/lib/components/sidenav/sidenav.stories.ts",
                "deprecated": false,
                "deprecationMessage": "",
                "type": "Story<SidenavComponent>",
                "defaultValue": "(args: SidenavComponent) => ({\n  props: args,\n})"
            }
        ],
        "functions": [],
        "typealiases": [],
        "enumerations": [],
        "groupedVariables": {
            "projects/ui-components/src/lib/components/sidenav/sidenav.stories.ts": [
                {
                    "name": "Default",
                    "ctype": "miscellaneous",
                    "subtype": "variable",
                    "file": "projects/ui-components/src/lib/components/sidenav/sidenav.stories.ts",
                    "deprecated": false,
                    "deprecationMessage": "",
                    "type": "",
                    "defaultValue": "Template.bind({})"
                },
                {
                    "name": "Template",
                    "ctype": "miscellaneous",
                    "subtype": "variable",
                    "file": "projects/ui-components/src/lib/components/sidenav/sidenav.stories.ts",
                    "deprecated": false,
                    "deprecationMessage": "",
                    "type": "Story<SidenavComponent>",
                    "defaultValue": "(args: SidenavComponent) => ({\n  props: args,\n})"
                }
            ]
        },
        "groupedFunctions": {},
        "groupedEnumerations": {},
        "groupedTypeAliases": {}
    },
    "routes": [],
    "coverage": {
        "count": 0,
        "status": "low",
        "files": [
            {
                "filePath": "projects/ui-components/src/lib/components/sidenav/sidenav-item/sidenav-item.component.ts",
                "type": "component",
                "linktype": "component",
                "name": "SidenavItemComponent",
                "coveragePercent": 0,
                "coverageCount": "0/14",
                "status": "low"
            },
            {
                "filePath": "projects/ui-components/src/lib/components/sidenav/sidenav-subitem/sidenav-subitem.component.ts",
                "type": "component",
                "linktype": "component",
                "name": "SidenavSubitemComponent",
                "coveragePercent": 0,
                "coverageCount": "0/3",
                "status": "low"
            },
            {
                "filePath": "projects/ui-components/src/lib/components/sidenav/sidenav.component.ts",
                "type": "component",
                "linktype": "component",
                "name": "SidenavComponent",
                "coveragePercent": 0,
                "coverageCount": "0/1",
                "status": "low"
            },
            {
                "filePath": "projects/ui-components/src/lib/components/sidenav/sidenav.stories.ts",
                "type": "variable",
                "linktype": "miscellaneous",
                "linksubtype": "variable",
                "name": "Default",
                "coveragePercent": 0,
                "coverageCount": "0/1",
                "status": "low"
            },
            {
                "filePath": "projects/ui-components/src/lib/components/sidenav/sidenav.stories.ts",
                "type": "variable",
                "linktype": "miscellaneous",
                "linksubtype": "variable",
                "name": "Template",
                "coveragePercent": 0,
                "coverageCount": "0/1",
                "status": "low"
            },
            {
                "filePath": "projects/ui-components/src/lib/components/typography/typography.component.ts",
                "type": "component",
                "linktype": "component",
                "name": "TypographyComponent",
                "coveragePercent": 0,
                "coverageCount": "0/1",
                "status": "low"
            },
            {
                "filePath": "src/app/app.component.ts",
                "type": "component",
                "linktype": "component",
                "name": "AppComponent",
                "coveragePercent": 0,
                "coverageCount": "0/2",
                "status": "low"
            }
        ]
    }
}